Metadata-Version: 2.1
Name: AI-PROJECT-JLK
Version: 0.0.1
Summary: This is for a project I took with SRJC.  
Author: JediL
Author-email: HeyDidej101@gmail.com
